{
  "service_enabled": true,
  "members": [
    {
      "nickname": "세라자드",
      "device_id": "0242e94b-654e-4e19-b114-a05a40c0c598",
      "enabled": true,
      "note": "본인"
    },
    {
      "nickname": "천마존",
      "device_id": ["6e8ddb84-b482-4d3b-9d34-ca3890c252cb","0a0c8006-7117-471d-b5fc-85a4e6d547c5"],
      "enabled": true,
      "note": "문파장"
    },
    {
      "nickname": "냉오리",
      "device_id": "45e93dd9-7375-492c-97a3-86ba7c0b309f",
      "enabled": true,
      "note": "문파원"
    },
    {
      "nickname": "김똥",
      "device_id": "f06cfc73-716a-490e-a368-43760fe7ef7e",
      "enabled": true,
      "note": "문파원"
    },
    {
      "nickname": "Victor",
      "device_id": ["205bba3e-5e8c-4470-964a-ba9e3abcb2a5","c7407055-83d3-474f-9814-7466822f0de5"],
      "enabled": true,
      "note": "문파원"
    },
    {
      "nickname": "몬이",
      "device_id": "d8b895bb-a9e6-46fe-bf5e-fdc015069588",
      "enabled": true,
      "note": "문파원"
    },
    {
      "nickname": "배신자",
      "device_id": "48120094-631d-4d9c-be59-1cf26d845190",
      "enabled": true,
      "note": "문파원"
    },
    {
      "nickname": "아이온짱",
      "device_id": "68cf7eb3-29d6-49ca-a8b9-1814be88e4ac",
      "enabled": true,
      "note": "문파원"
    },
    {
      "nickname": "여히땅1",
      "device_id": "739a8f6a-5bb0-4f0b-a622-a01938210a79",
      "enabled": true,
      "note": "문파원"
    },
    {
      "nickname": "청휴",
      "device_id": "8d835efe-0dff-4b9e-9080-6f47caf58ed6",
      "enabled": true,
      "note": "문파원"
    },
    {
      "nickname": "궁극의방어",
      "device_id": "99ab6e7e-068a-4c16-bd3c-5fb7f96fc2be",
      "enabled": true,
      "note": "장로"
    },
    {
      "nickname": "토즈",
      "device_id": "1395ac8a-bbae-4d88-91fa-a9b69e4aa575",
      "enabled": true,
      "note": "장로"
    },
    {
      "nickname": "큐티푸우",
      "device_id": "6a29724a-c802-4b31-864c-61744ab71fbf",
      "enabled": true,
      "note": "문파원"
    }
  ],
  "version": 13,
  "updated_at": "2026-06-29"
}
